divider/divider.v
`timescale 1ns/1ps

module divider (
output reg[63:0] quotient,
output reg [63:0] remainder_out,
output ready,
input [63:0] a, b
);

reg [127:0] remainder, divisor;
reg [7:0] ctr;
reg clk;
wire ready;
wire nega, negb;

assign ready = (ctr >= 65) ? 1:0;
assign nega = a[63];
assign negb = b[63];

always begin
  #2 clk = ~clk;
end

always@(a|b)begin
    quotient <= 0;
    ctr <=0;
    remainder = (nega) ? {64'b0, -a} : {64'b0,a};
    divisor = (negb) ? (-b << 64) : (b<<64);
    clk=0;
end

always@(clk)
begin

if(ctr < 65)begin
    remainder = remainder - divisor;
    quotient = quotient <<1;
    if(remainder[127]==1)begin
        remainder = remainder + divisor;
        quotient[0] <= 0;
    end else begin
        quotient[0] <=1;
    end
    divisor = divisor >> 1;
    ctr=ctr+1;
end
if(ctr >= 65) begin
    if(nega !== negb) begin
      quotient[63] <= 1;
    end
    remainder_out[63:0] <= remainder[63:0];
end
end

endmodule

divider/divider_tb.v
`timescale 1ns/1ps
`include "divider.v"

module divider_tb();

wire [63:0] quotient;
wire [63:0] remainder;
wire rdy;
reg [63:0] a,b;

divider M1 (quotient, remainder, rdy, a, b);


initial begin // Time Out
#10000 $finish; // Stopwatch
end

initial begin
    $dumpfile("divider.vcd");
    $dumpvars(0, divider_tb);
a <= 26;
b <= 4;

end

endmodule

divider/divider.vcd
$date
	Wed Dec 07 19:24:50 2022
$end
$version
	Icarus Verilog
$end
$timescale
	1ps
$end
$scope module divider_tb $end
$var wire 64 ! remainder [63:0] $end
$var wire 1 " rdy $end
$var wire 64 # quotient [63:0] $end
$var reg 64 $ a [63:0] $end
$var reg 64 % b [63:0] $end
$scope module M1 $end
$var wire 64 & a [63:0] $end
$var wire 64 ' b [63:0] $end
$var wire 1 " ready $end
$var wire 1 ( negb $end
$var wire 1 ) nega $end
$var reg 1 * clk $end
$var reg 8 + ctr [7:0] $end
$var reg 128 , divisor [127:0] $end
$var reg 64 - quotient [63:0] $end
$var reg 128 . remainder [127:0] $end
$var reg 64 / remainder_out [63:0] $end
$upscope $end
$upscope $end
$enddefinitions $end
$comment Show the parameter values. $end
$dumpall
$end
#0
$dumpvars
bx /
b11010 .
b0 -
b1000000000000000000000000000000000000000000000000000000000000000000 ,
b0 +
0*
0)
0(
b100 '
b11010 &
b100 %
b11010 $
b0 #
0"
bx !
$end
#2000
b1 +
b100000000000000000000000000000000000000000000000000000000000000000 ,
b11010 .
1*
#4000
b10 +
b10000000000000000000000000000000000000000000000000000000000000000 ,
b11010 .
0*
#6000
b11 +
b1000000000000000000000000000000000000000000000000000000000000000 ,
b11010 .
1*
#8000
b100 +
b100000000000000000000000000000000000000000000000000000000000000 ,
b11010 .
0*
#10000
b101 +
b10000000000000000000000000000000000000000000000000000000000000 ,
b11010 .
1*
#12000
b110 +
b1000000000000000000000000000000000000000000000000000000000000 ,
b11010 .
0*
#14000
b111 +
b100000000000000000000000000000000000000000000000000000000000 ,
b11010 .
1*
#16000
b1000 +
b10000000000000000000000000000000000000000000000000000000000 ,
b11010 .
0*
#18000
b1001 +
b1000000000000000000000000000000000000000000000000000000000 ,
b11010 .
1*
#20000
b1010 +
b100000000000000000000000000000000000000000000000000000000 ,
b11010 .
0*
#22000
b1011 +
b10000000000000000000000000000000000000000000000000000000 ,
b11010 .
1*
#24000
b1100 +
b1000000000000000000000000000000000000000000000000000000 ,
b11010 .
0*
#26000
b1101 +
b100000000000000000000000000000000000000000000000000000 ,
b11010 .
1*
#28000
b1110 +
b10000000000000000000000000000000000000000000000000000 ,
b11010 .
0*
#30000
b1111 +
b1000000000000000000000000000000000000000000000000000 ,
b11010 .
1*
#32000
b10000 +
b100000000000000000000000000000000000000000000000000 ,
b11010 .
0*
#34000
b10001 +
b10000000000000000000000000000000000000000000000000 ,
b11010 .
1*
#36000
b10010 +
b1000000000000000000000000000000000000000000000000 ,
b11010 .
0*
#38000
b10011 +
b100000000000000000000000000000000000000000000000 ,
b11010 .
1*
#40000
b10100 +
b10000000000000000000000000000000000000000000000 ,
b11010 .
0*
#42000
b10101 +
b1000000000000000000000000000000000000000000000 ,
b11010 .
1*
#44000
b10110 +
b100000000000000000000000000000000000000000000 ,
b11010 .
0*
#46000
b10111 +
b10000000000000000000000000000000000000000000 ,
b11010 .
1*
#48000
b11000 +
b1000000000000000000000000000000000000000000 ,
b11010 .
0*
#50000
b11001 +
b100000000000000000000000000000000000000000 ,
b11010 .
1*
#52000
b11010 +
b10000000000000000000000000000000000000000 ,
b11010 .
0*
#54000
b11011 +
b1000000000000000000000000000000000000000 ,
b11010 .
1*
#56000
b11100 +
b100000000000000000000000000000000000000 ,
b11010 .
0*
#58000
b11101 +
b10000000000000000000000000000000000000 ,
b11010 .
1*
#60000
b11110 +
b1000000000000000000000000000000000000 ,
b11010 .
0*
#62000
b11111 +
b100000000000000000000000000000000000 ,
b11010 .
1*
#64000
b100000 +
b10000000000000000000000000000000000 ,
b11010 .
0*
#66000
b100001 +
b1000000000000000000000000000000000 ,
b11010 .
1*
#68000
b100010 +
b100000000000000000000000000000000 ,
b11010 .
0*
#70000
b100011 +
b10000000000000000000000000000000 ,
b11010 .
1*
#72000
b100100 +
b1000000000000000000000000000000 ,
b11010 .
0*
#74000
b100101 +
b100000000000000000000000000000 ,
b11010 .
1*
#76000
b100110 +
b10000000000000000000000000000 ,
b11010 .
0*
#78000
b100111 +
b1000000000000000000000000000 ,
b11010 .
1*
#80000
b101000 +
b100000000000000000000000000 ,
b11010 .
0*
#82000
b101001 +
b10000000000000000000000000 ,
b11010 .
1*
#84000
b101010 +
b1000000000000000000000000 ,
b11010 .
0*
#86000
b101011 +
b100000000000000000000000 ,
b11010 .
1*
#88000
b101100 +
b10000000000000000000000 ,
b11010 .
0*
#90000
b101101 +
b1000000000000000000000 ,
b11010 .
1*
#92000
b101110 +
b100000000000000000000 ,
b11010 .
0*
#94000
b101111 +
b10000000000000000000 ,
b11010 .
1*
#96000
b110000 +
b1000000000000000000 ,
b11010 .
0*
#98000
b110001 +
b100000000000000000 ,
b11010 .
1*
#100000
b110010 +
b10000000000000000 ,
b11010 .
0*
#102000
b110011 +
b1000000000000000 ,
b11010 .
1*
#104000
b110100 +
b100000000000000 ,
b11010 .
0*
#106000
b110101 +
b10000000000000 ,
b11010 .
1*
#108000
b110110 +
b1000000000000 ,
b11010 .
0*
#110000
b110111 +
b100000000000 ,
b11010 .
1*
#112000
b111000 +
b10000000000 ,
b11010 .
0*
#114000
b111001 +
b1000000000 ,
b11010 .
1*
#116000
b111010 +
b100000000 ,
b11010 .
0*
#118000
b111011 +
b10000000 ,
b11010 .
1*
#120000
b111100 +
b1000000 ,
b11010 .
0*
#122000
b111101 +
b100000 ,
b11010 .
1*
#124000
b111110 +
b10000 ,
b11010 .
0*
#126000
b1 #
b1 -
b111111 +
b1000 ,
b1010 .
1*
#128000
b1000000 +
b100 ,
b11 #
b11 -
b10 .
0*
#130000
b10 !
b10 /
1"
b1000001 +
b10 ,
b110 #
b110 -
b10 .
1*
