sources/divider.v
`timescale 1ns/1ps

module divider (
output [63:0] quotient,
output [127:0] remainder,
output ready,
input [127:0] a, b,
input reset, clk
);

reg [63:0] quotient;
reg [127:0] remainder, divisor, dividend;
reg [7:0] ctr;
reg ready;

always@(posedge clk)
begin
  if(reset)begin
    quotient <= 0;
    ctr <=0;
    ready<=0;
    remainder [127:0] <= a[127:0];
    divisor = b << 64;
  end

if(ctr < 65)begin
    remainder = remainder - divisor;
    quotient = quotient <<1;
    if(remainder[127]==1)begin
        remainder = remainder + divisor;
        quotient[0] <= 0;
    end else begin
        quotient[0] <=1;
    end
    divisor = divisor >> 1;
    ctr=ctr+1;
end
if(ctr>=65) begin
    ready<=1;
end
end

endmodule

multiplier/divider/divider_tb.v
`timescale 1ns/1ps
`include "divider.v"

module divider_tb();

wire [63:0] quotient;
wire [127:0] remainder;
wire rdy;
reg [127:0] a,b;
reg rst,clk;

divider M1 (quotient, remainder, rdy, a, b, rst, clk);

always #10 clk = !clk;

initial begin
    $dumpfile("divider.vcd");
    $dumpvars(0, divider_tb);
a = 500;
b = 25;
rst = 1;
clk=1;
#1 rst=0;

while(rdy==0) begin
    @(posedge clk);
end

rst = 1;
#200 $finish;

end

endmodule

multiplier/divider/divider.vcd
$date
	Mon Nov 28 20:47:14 2022
$end
$version
	Icarus Verilog
$end
$timescale
	1ps
$end
$scope module divider_tb $end
$var wire 128 ! remainder [127:0] $end
$var wire 1 " rdy $end
$var wire 64 # quotient [63:0] $end
$var reg 128 $ a [127:0] $end
$var reg 128 % b [127:0] $end
$var reg 1 & clk $end
$var reg 1 ' rst $end
$scope module M1 $end
$var wire 128 ( a [127:0] $end
$var wire 128 ) b [127:0] $end
$var wire 1 & clk $end
$var wire 1 ' reset $end
$var reg 8 * ctr [7:0] $end
$var reg 128 + divisor [127:0] $end
$var reg 64 , quotient [63:0] $end
$var reg 1 " ready $end
$var reg 128 - remainder [127:0] $end
$upscope $end
$upscope $end
$enddefinitions $end
$comment Show the parameter values. $end
$dumpall
$end
#0
$dumpvars
b111110100 -
b0 ,
b110010000000000000000000000000000000000000000000000000000000000000000 +
b0 *
b11001 )
b111110100 (
1'
1&
b11001 %
b111110100 $
b0 #
0"
b111110100 !
$end
#1000
0'
#10000
0&
#20000
b1 *
b11001000000000000000000000000000000000000000000000000000000000000000 +
b111110100 !
b111110100 -
1&
#30000
0&
#40000
b10 *
b1100100000000000000000000000000000000000000000000000000000000000000 +
b111110100 !
b111110100 -
1&
#50000
0&
#60000
b11 *
b110010000000000000000000000000000000000000000000000000000000000000 +
b111110100 !
b111110100 -
1&
#70000
0&
#80000
b100 *
b11001000000000000000000000000000000000000000000000000000000000000 +
b111110100 !
b111110100 -
1&
#90000
0&
#100000
b101 *
b1100100000000000000000000000000000000000000000000000000000000000 +
b111110100 !
b111110100 -
1&
#110000
0&
#120000
b110 *
b110010000000000000000000000000000000000000000000000000000000000 +
b111110100 !
b111110100 -
1&
#130000
0&
#140000
b111 *
b11001000000000000000000000000000000000000000000000000000000000 +
b111110100 !
b111110100 -
1&
#150000
0&
#160000
b1000 *
b1100100000000000000000000000000000000000000000000000000000000 +
b111110100 !
b111110100 -
1&
#170000
0&
#180000
b1001 *
b110010000000000000000000000000000000000000000000000000000000 +
b111110100 !
b111110100 -
1&
#190000
0&
#200000
b1010 *
b11001000000000000000000000000000000000000000000000000000000 +
b111110100 !
b111110100 -
1&
#210000
0&
#220000
b1011 *
b1100100000000000000000000000000000000000000000000000000000 +
b111110100 !
b111110100 -
1&
#230000
0&
#240000
b1100 *
b110010000000000000000000000000000000000000000000000000000 +
b111110100 !
b111110100 -
1&
#250000
0&
#260000
b1101 *
b11001000000000000000000000000000000000000000000000000000 +
b111110100 !
b111110100 -
1&
#270000
0&
#280000
b1110 *
b1100100000000000000000000000000000000000000000000000000 +
b111110100 !
b111110100 -
1&
#290000
0&
#300000
b1111 *
b110010000000000000000000000000000000000000000000000000 +
b111110100 !
b111110100 -
1&
#310000
0&
#320000
b10000 *
b11001000000000000000000000000000000000000000000000000 +
b111110100 !
b111110100 -
1&
#330000
0&
#340000
b10001 *
b1100100000000000000000000000000000000000000000000000 +
b111110100 !
b111110100 -
1&
#350000
0&
#360000
b10010 *
b110010000000000000000000000000000000000000000000000 +
b111110100 !
b111110100 -
1&
#370000
0&
#380000
b10011 *
b11001000000000000000000000000000000000000000000000 +
b111110100 !
b111110100 -
1&
#390000
0&
#400000
b10100 *
b1100100000000000000000000000000000000000000000000 +
b111110100 !
b111110100 -
1&
#410000
0&
#420000
b10101 *
b110010000000000000000000000000000000000000000000 +
b111110100 !
b111110100 -
1&
#430000
0&
#440000
b10110 *
b11001000000000000000000000000000000000000000000 +
b111110100 !
b111110100 -
1&
#450000
0&
#460000
b10111 *
b1100100000000000000000000000000000000000000000 +
b111110100 !
b111110100 -
1&
#470000
0&
#480000
b11000 *
b110010000000000000000000000000000000000000000 +
b111110100 !
b111110100 -
1&
#490000
0&
#500000
b11001 *
b11001000000000000000000000000000000000000000 +
b111110100 !
b111110100 -
1&
#510000
0&
#520000
b11010 *
b1100100000000000000000000000000000000000000 +
b111110100 !
b111110100 -
1&
#530000
0&
#540000
b11011 *
b110010000000000000000000000000000000000000 +
b111110100 !
b111110100 -
1&
#550000
0&
#560000
b11100 *
b11001000000000000000000000000000000000000 +
b111110100 !
b111110100 -
1&
#570000
0&
#580000
b11101 *
b1100100000000000000000000000000000000000 +
b111110100 !
b111110100 -
1&
#590000
0&
#600000
b11110 *
b110010000000000000000000000000000000000 +
b111110100 !
b111110100 -
1&
#610000
0&
#620000
b11111 *
b11001000000000000000000000000000000000 +
b111110100 !
b111110100 -
1&
#630000
0&
#640000
b100000 *
b1100100000000000000000000000000000000 +
b111110100 !
b111110100 -
1&
#650000
0&
#660000
b100001 *
b110010000000000000000000000000000000 +
b111110100 !
b111110100 -
1&
#670000
0&
#680000
b100010 *
b11001000000000000000000000000000000 +
b111110100 !
b111110100 -
1&
#690000
0&
#700000
b100011 *
b1100100000000000000000000000000000 +
b111110100 !
b111110100 -
1&
#710000
0&
#720000
b100100 *
b110010000000000000000000000000000 +
b111110100 !
b111110100 -
1&
#730000
0&
#740000
b100101 *
b11001000000000000000000000000000 +
b111110100 !
b111110100 -
1&
#750000
0&
#760000
b100110 *
b1100100000000000000000000000000 +
b111110100 !
b111110100 -
1&
#770000
0&
#780000
b100111 *
b110010000000000000000000000000 +
b111110100 !
b111110100 -
1&
#790000
0&
#800000
b101000 *
b11001000000000000000000000000 +
b111110100 !
b111110100 -
1&
#810000
0&
#820000
b101001 *
b1100100000000000000000000000 +
b111110100 !
b111110100 -
1&
#830000
0&
#840000
b101010 *
b110010000000000000000000000 +
b111110100 !
b111110100 -
1&
#850000
0&
#860000
b101011 *
b11001000000000000000000000 +
b111110100 !
b111110100 -
1&
#870000
0&
#880000
b101100 *
b1100100000000000000000000 +
b111110100 !
b111110100 -
1&
#890000
0&
#900000
b101101 *
b110010000000000000000000 +
b111110100 !
b111110100 -
1&
#910000
0&
#920000
b101110 *
b11001000000000000000000 +
b111110100 !
b111110100 -
1&
#930000
0&
#940000
b101111 *
b1100100000000000000000 +
b111110100 !
b111110100 -
1&
#950000
0&
#960000
b110000 *
b110010000000000000000 +
b111110100 !
b111110100 -
1&
#970000
0&
#980000
b110001 *
b11001000000000000000 +
b111110100 !
b111110100 -
1&
#990000
0&
#1000000
b110010 *
b1100100000000000000 +
b111110100 !
b111110100 -
1&
#1010000
0&
#1020000
b110011 *
b110010000000000000 +
b111110100 !
b111110100 -
1&
#1030000
0&
#1040000
b110100 *
b11001000000000000 +
b111110100 !
b111110100 -
1&
#1050000
0&
#1060000
b110101 *
b1100100000000000 +
b111110100 !
b111110100 -
1&
#1070000
0&
#1080000
b110110 *
b110010000000000 +
b111110100 !
b111110100 -
1&
#1090000
0&
#1100000
b110111 *
b11001000000000 +
b111110100 !
b111110100 -
1&
#1110000
0&
#1120000
b111000 *
b1100100000000 +
b111110100 !
b111110100 -
1&
#1130000
0&
#1140000
b111001 *
b110010000000 +
b111110100 !
b111110100 -
1&
#1150000
0&
#1160000
b111010 *
b11001000000 +
b111110100 !
b111110100 -
1&
#1170000
0&
#1180000
b111011 *
b1100100000 +
b111110100 !
b111110100 -
1&
#1190000
0&
#1200000
b111100 *
b110010000 +
b111110100 !
b111110100 -
1&
#1210000
0&
#1220000
b1 #
b1 ,
b111101 *
b11001000 +
b1100100 !
b1100100 -
1&
#1230000
0&
#1240000
b111110 *
b1100100 +
b10 #
b10 ,
b1100100 !
b1100100 -
1&
#1250000
0&
#1260000
b111111 *
b110010 +
b101 #
b101 ,
b0 !
b0 -
1&
#1270000
0&
#1280000
b1000000 *
b11001 +
b1010 #
b1010 ,
b0 !
b0 -
1&
#1290000
0&
#1300000
1"
b1000001 *
b1100 +
b10100 #
b10100 ,
b0 !
b0 -
1&
#1310000
0&
#1320000
1'
1&
#1330000
0&
#1340000
b111110100 !
b111110100 -
1"
b0 *
b0 #
b0 ,
b110010000000000000000000000000000000000000000000000000000000000000000 +
1&
#1350000
0&
#1360000
0"
b0 *
b11001000000000000000000000000000000000000000000000000000000000000000 +
b111110100 !
b111110100 -
1&
#1370000
0&
#1380000
b0 *
b111110100 !
b111110100 -
b11001000000000000000000000000000000000000000000000000000000000000000 +
1&
#1390000
0&
#1400000
b0 *
b111110100 !
b111110100 -
b11001000000000000000000000000000000000000000000000000000000000000000 +
1&
#1410000
0&
#1420000
b0 *
b111110100 !
b111110100 -
b11001000000000000000000000000000000000000000000000000000000000000000 +
1&
#1430000
0&
#1440000
b0 *
b111110100 !
b111110100 -
b11001000000000000000000000000000000000000000000000000000000000000000 +
1&
#1450000
0&
#1460000
b0 *
b111110100 !
b111110100 -
b11001000000000000000000000000000000000000000000000000000000000000000 +
1&
#1470000
0&
#1480000
b0 *
b111110100 !
b111110100 -
b11001000000000000000000000000000000000000000000000000000000000000000 +
1&
#1490000
0&
#1500000
b0 *
b111110100 !
b111110100 -
b11001000000000000000000000000000000000000000000000000000000000000000 +
1&
#1510000
0&
#1520000
b0 *
b111110100 !
b111110100 -
b11001000000000000000000000000000000000000000000000000000000000000000 +
1&
