regfile/register_file.v


module register_file(
output [63:0] read_data_1, read_data_2,
input [63:0] write_reg_data,
input [4:0] read_1_addr, read_2_addr, write_addr,
input regWrite_en, clk, rst
);

reg [63:0] regArray [31:0];

assign read_data_1 = regArray[read_1_addr];
assign read_data_2 = regArray[read_2_addr];

always@(posedge clk) begin
    if(regWrite_en)begin
        regArray[write_addr]=write_reg_data;
    end
    if(rst==1) begin
        for(integer i=0; i<32; i=i+1) begin
            regArray[i] <= 64'b0;
        end
    end

    regArray[0] = 64'b0;
end



endmodule

regfile/register_file_tb.v
`timescale 1ns/1ps
`include "register_file.v"

module register_file_tb();
wire [63:0] read_data_1, read_data_2;
reg[63:0] write_reg_data;
reg[4:0] read_1_addr, read_2_addr,write_addr;
reg regWrite_en, clk, rst;

register_file m1 (
    read_data_1,
    read_data_2,
    write_reg_data,
    read_1_addr,
    read_1_addr,
    write_addr,
    regWrite_en,
    clk,
    rst
    );

always begin
    #10 clk = ~clk;
end

initial begin
    #1000 $finish;
end

initial begin

    $dumpfile("reg.vcd");
    $dumpvars(0, register_file_tb);
    clk = 0;
    #30  write_addr <= 16;
    #30  write_reg_data <= {6'h23, 5'd29, 5'd4, 16'h0000};


    #20 read_1_addr <= 16;

    #10 regWrite_en = 1;

    #10 rst = 1;
end

endmodule

regfile/reg.vcd
$date
	Fri Dec 09 15:06:23 2022
$end
$version
	Icarus Verilog
$end
$timescale
	1ps
$end
$scope module register_file_tb $end
$var wire 64 ! read_data_2 [63:0] $end
$var wire 64 " read_data_1 [63:0] $end
$var reg 1 # clk $end
$var reg 5 $ read_1_addr [4:0] $end
$var reg 1 % regWrite_en $end
$var reg 1 & rst $end
$var reg 5 ' write_addr [4:0] $end
$var reg 64 ( write_reg_data [63:0] $end
$scope module m1 $end
$var wire 1 # clk $end
$var wire 5 ) read_1_addr [4:0] $end
$var wire 5 * read_2_addr [4:0] $end
$var wire 64 + read_data_1 [63:0] $end
$var wire 64 , read_data_2 [63:0] $end
$var wire 1 % regWrite_en $end
$var wire 1 & rst $end
$var wire 5 - write_addr [4:0] $end
$var wire 64 . write_reg_data [63:0] $end
$scope begin $ivl_for_loop0 $end
$var integer 32 / i [31:0] $end
$upscope $end
$upscope $end
$upscope $end
$enddefinitions $end
$comment Show the parameter values. $end
$dumpall
$end
#0
$dumpvars
bx /
bx .
bx -
bx ,
bx +
bx *
bx )
bx (
bx '
x&
x%
bx $
0#
bx "
bx !
$end
#10000
1#
#20000
0#
#30000
b10000 '
b10000 -
1#
#40000
0#
#50000
1#
#60000
b10001111101001000000000000000000 (
b10001111101001000000000000000000 .
0#
#70000
1#
#80000
b10000 $
b10000 )
b10000 *
0#
#90000
b10001111101001000000000000000000 "
b10001111101001000000000000000000 +
b10001111101001000000000000000000 !
b10001111101001000000000000000000 ,
1#
1%
#100000
0#
1&
#110000
b0 "
b0 +
b0 !
b0 ,
b100000 /
1#
#120000
0#
#130000
b100000 /
b0 "
b0 +
b0 !
b0 ,
1#
#140000
0#
#150000
b100000 /
b0 "
b0 +
b0 !
b0 ,
1#
#160000
0#
#170000
b100000 /
b0 "
b0 +
b0 !
b0 ,
1#
#180000
0#
#190000
b100000 /
b0 "
b0 +
b0 !
b0 ,
1#
#200000
0#
#210000
b100000 /
b0 "
b0 +
b0 !
b0 ,
1#
#220000
0#
#230000
b100000 /
b0 "
b0 +
b0 !
b0 ,
1#
#240000
0#
#250000
b100000 /
b0 "
b0 +
b0 !
b0 ,
1#
#260000
0#
#270000
b100000 /
b0 "
b0 +
b0 !
b0 ,
1#
#280000
0#
#290000
b100000 /
b0 "
b0 +
b0 !
b0 ,
1#
#300000
0#
#310000
b100000 /
b0 "
b0 +
b0 !
b0 ,
1#
#320000
0#
#330000
b100000 /
b0 "
b0 +
b0 !
b0 ,
1#
#340000
0#
#350000
b100000 /
b0 "
b0 +
b0 !
b0 ,
1#
#360000
0#
#370000
b100000 /
b0 "
b0 +
b0 !
b0 ,
1#
#380000
0#
#390000
b100000 /
b0 "
b0 +
b0 !
b0 ,
1#
#400000
0#
#410000
b100000 /
b0 "
b0 +
b0 !
b0 ,
1#
#420000
0#
#430000
b100000 /
b0 "
b0 +
b0 !
b0 ,
1#
#440000
0#
#450000
b100000 /
b0 "
b0 +
b0 !
b0 ,
1#
#460000
0#
#470000
b100000 /
b0 "
b0 +
b0 !
b0 ,
1#
#480000
0#
#490000
b100000 /
b0 "
b0 +
b0 !
b0 ,
1#
#500000
0#
#510000
b100000 /
b0 "
b0 +
b0 !
b0 ,
1#
#520000
0#
#530000
b100000 /
b0 "
b0 +
b0 !
b0 ,
1#
#540000
0#
#550000
b100000 /
b0 "
b0 +
b0 !
b0 ,
1#
#560000
0#
#570000
b100000 /
b0 "
b0 +
b0 !
b0 ,
1#
#580000
0#
#590000
b100000 /
b0 "
b0 +
b0 !
b0 ,
1#
#600000
0#
#610000
b100000 /
b0 "
b0 +
b0 !
b0 ,
1#
#620000
0#
#630000
b100000 /
b0 "
b0 +
b0 !
b0 ,
1#
#640000
0#
#650000
b100000 /
b0 "
b0 +
b0 !
b0 ,
1#
#660000
0#
#670000
b100000 /
b0 "
b0 +
b0 !
b0 ,
1#
#680000
0#
#690000
b100000 /
b0 "
b0 +
b0 !
b0 ,
1#
#700000
0#
#710000
b100000 /
b0 "
b0 +
b0 !
b0 ,
1#
#720000
0#
#730000
b100000 /
b0 "
b0 +
b0 !
b0 ,
1#
#740000
0#
#750000
b100000 /
b0 "
b0 +
b0 !
b0 ,
1#
#760000
0#
#770000
b100000 /
b0 "
b0 +
b0 !
b0 ,
1#
#780000
0#
#790000
b100000 /
b0 "
b0 +
b0 !
b0 ,
1#
#800000
0#
#810000
b100000 /
b0 "
b0 +
b0 !
b0 ,
1#
#820000
0#
#830000
b100000 /
b0 "
b0 +
b0 !
b0 ,
1#
#840000
0#
#850000
b100000 /
b0 "
b0 +
b0 !
b0 ,
1#
#860000
0#
#870000
b100000 /
b0 "
b0 +
b0 !
b0 ,
1#
#880000
0#
#890000
b100000 /
b0 "
b0 +
b0 !
b0 ,
1#
#900000
0#
#910000
b100000 /
b0 "
b0 +
b0 !
b0 ,
1#
#920000
0#
#930000
b100000 /
b0 "
b0 +
b0 !
b0 ,
1#
#940000
0#
#950000
b100000 /
b0 "
b0 +
b0 !
b0 ,
1#
#960000
0#
#970000
b100000 /
b0 "
b0 +
b0 !
b0 ,
1#
#980000
0#
#990000
b100000 /
b0 "
b0 +
b0 !
b0 ,
1#
