multiplier/multiplier.v
`timescale 1ns/1ps
module multiplier(
output [127:0] product,
output ready,
input wire[63:0] a, b
);

reg [127:0] product, mc;
reg [63:0] mp;
reg [6:0] ctr;
reg clk;
wire ready;

wire nega, negb;

assign nega = a[63];
assign negb = b[63];
assign ready = (ctr>=63) ? 1:0;

always begin
  #2 clk = ~clk;
end

always@(a|b) begin
    product <= 0;
    mp <= (nega) ? -a : a;
    mc <= (negb) ? -b : b;
    mc[127:64] <=64'b0;
    clk <= 0;
    ctr = 0;
  end

always@(clk)
begin 
if(ctr<63)begin
  if(mp[0]==1)begin
    product <= product+ mc;
    end
  mc = mc << 1;
  mp = mp >>1;
  ctr =ctr+1;
end
if(ctr>=63)begin
      if(a[63] !== b[63]) begin
      product[127] <= 1;
    end
end
end


endmodule

testbenches/mpliertb.v
`timescale 1ns/1ps
`include "multiplier.v"

module mpliertb();

wire [127:0] product;
wire rdy;
reg [63:0] a,b;





multiplier M1 (product, rdy, a, b);



initial begin

    $dumpfile("mpliertb.vcd");
    $dumpvars(0, mpliertb);
a = 659;
b = -42;

#128 ;

a=400;
b=-5;
#128 $finish;

end

endmodule

multiplier/mpliertb.vcd
$date
	Wed Dec 07 15:18:43 2022
$end
$version
	Icarus Verilog
$end
$timescale
	1ps
$end
$scope module mpliertb $end
$var wire 1 ! rdy $end
$var wire 128 " product [127:0] $end
$var reg 64 # a [63:0] $end
$var reg 64 $ b [63:0] $end
$scope module M1 $end
$var wire 64 % a [63:0] $end
$var wire 64 & b [63:0] $end
$var wire 1 ! ready $end
$var wire 1 ' negb $end
$var wire 1 ( nega $end
$var reg 1 ) clk $end
$var reg 7 * ctr [6:0] $end
$var reg 128 + mc [127:0] $end
$var reg 64 , mp [63:0] $end
$var reg 128 - product [127:0] $end
$upscope $end
$upscope $end
$enddefinitions $end
$comment Show the parameter values. $end
$dumpall
$end
#0
$dumpvars
b101010 -
b101001001 ,
b1010100 +
b1 *
0)
0(
1'
b1111111111111111111111111111111111111111111111111111111111010110 &
b1010010011 %
b1111111111111111111111111111111111111111111111111111111111010110 $
b1010010011 #
b101010 "
0!
$end
#2000
b1111110 "
b1111110 -
b10 *
b10100100 ,
b10101000 +
1)
#4000
b11 *
b1010010 ,
b101010000 +
0)
#6000
b100 *
b101001 ,
b1010100000 +
1)
#8000
b1100011110 "
b1100011110 -
b101 *
b10100 ,
b10101000000 +
0)
#10000
b110 *
b1010 ,
b101010000000 +
1)
#12000
b111 *
b101 ,
b1010100000000 +
0)
#14000
b1100000011110 "
b1100000011110 -
b1000 *
b10 ,
b10101000000000 +
1)
#16000
b1001 *
b1 ,
b101010000000000 +
0)
#18000
b110110000011110 "
b110110000011110 -
b1010 *
b0 ,
b1010100000000000 +
1)
#20000
b1011 *
b10101000000000000 +
0)
#22000
b1100 *
b101010000000000000 +
1)
#24000
b1101 *
b1010100000000000000 +
0)
#26000
b1110 *
b10101000000000000000 +
1)
#28000
b1111 *
b101010000000000000000 +
0)
#30000
b10000 *
b1010100000000000000000 +
1)
#32000
b10001 *
b10101000000000000000000 +
0)
#34000
b10010 *
b101010000000000000000000 +
1)
#36000
b10011 *
b1010100000000000000000000 +
0)
#38000
b10100 *
b10101000000000000000000000 +
1)
#40000
b10101 *
b101010000000000000000000000 +
0)
#42000
b10110 *
b1010100000000000000000000000 +
1)
#44000
b10111 *
b10101000000000000000000000000 +
0)
#46000
b11000 *
b101010000000000000000000000000 +
1)
#48000
b11001 *
b1010100000000000000000000000000 +
0)
#50000
b11010 *
b10101000000000000000000000000000 +
1)
#52000
b11011 *
b101010000000000000000000000000000 +
0)
#54000
b11100 *
b1010100000000000000000000000000000 +
1)
#56000
b11101 *
b10101000000000000000000000000000000 +
0)
#58000
b11110 *
b101010000000000000000000000000000000 +
1)
#60000
b11111 *
b1010100000000000000000000000000000000 +
0)
#62000
b100000 *
b10101000000000000000000000000000000000 +
1)
#64000
b100001 *
b101010000000000000000000000000000000000 +
0)
#66000
b100010 *
b1010100000000000000000000000000000000000 +
1)
#68000
b100011 *
b10101000000000000000000000000000000000000 +
0)
#70000
b100100 *
b101010000000000000000000000000000000000000 +
1)
#72000
b100101 *
b1010100000000000000000000000000000000000000 +
0)
#74000
b100110 *
b10101000000000000000000000000000000000000000 +
1)
#76000
b100111 *
b101010000000000000000000000000000000000000000 +
0)
#78000
b101000 *
b1010100000000000000000000000000000000000000000 +
1)
#80000
b101001 *
b10101000000000000000000000000000000000000000000 +
0)
#82000
b101010 *
b101010000000000000000000000000000000000000000000 +
1)
#84000
b101011 *
b1010100000000000000000000000000000000000000000000 +
0)
#86000
b101100 *
b10101000000000000000000000000000000000000000000000 +
1)
#88000
b101101 *
b101010000000000000000000000000000000000000000000000 +
0)
#90000
b101110 *
b1010100000000000000000000000000000000000000000000000 +
1)
#92000
b101111 *
b10101000000000000000000000000000000000000000000000000 +
0)
#94000
b110000 *
b101010000000000000000000000000000000000000000000000000 +
1)
#96000
b110001 *
b1010100000000000000000000000000000000000000000000000000 +
0)
#98000
b110010 *
b10101000000000000000000000000000000000000000000000000000 +
1)
#100000
b110011 *
b101010000000000000000000000000000000000000000000000000000 +
0)
#102000
b110100 *
b1010100000000000000000000000000000000000000000000000000000 +
1)
#104000
b110101 *
b10101000000000000000000000000000000000000000000000000000000 +
0)
#106000
b110110 *
b101010000000000000000000000000000000000000000000000000000000 +
1)
#108000
b110111 *
b1010100000000000000000000000000000000000000000000000000000000 +
0)
#110000
b111000 *
b10101000000000000000000000000000000000000000000000000000000000 +
1)
#112000
b111001 *
b101010000000000000000000000000000000000000000000000000000000000 +
0)
#114000
b111010 *
b1010100000000000000000000000000000000000000000000000000000000000 +
1)
#116000
b111011 *
b10101000000000000000000000000000000000000000000000000000000000000 +
0)
#118000
b111100 *
b101010000000000000000000000000000000000000000000000000000000000000 +
1)
#120000
b111101 *
b1010100000000000000000000000000000000000000000000000000000000000000 +
0)
#122000
b111110 *
b10101000000000000000000000000000000000000000000000000000000000000000 +
1)
#124000
b10000000000000000000000000000000000000000000000000000000000000000000000000000000000000000000000000000000000000000110110000011110 "
b10000000000000000000000000000000000000000000000000000000000000000000000000000000000000000000000000000000000000000110110000011110 -
1!
b111111 *
b101010000000000000000000000000000000000000000000000000000000000000000 +
0)
#126000
1)
#128000
b101 +
b110010000 ,
b0 "
b0 -
0!
b0 *
0)
b1111111111111111111111111111111111111111111111111111111111111011 $
b1111111111111111111111111111111111111111111111111111111111111011 &
b110010000 #
b110010000 %
#130000
b1 *
b11001000 ,
b1010 +
1)
#132000
b10 *
b1100100 ,
b10100 +
0)
#134000
b11 *
b110010 ,
b101000 +
1)
#136000
b100 *
b11001 ,
b1010000 +
0)
#138000
b1010000 "
b1010000 -
b101 *
b1100 ,
b10100000 +
1)
#140000
b110 *
b110 ,
b101000000 +
0)
#142000
b111 *
b11 ,
b1010000000 +
1)
#144000
b1011010000 "
b1011010000 -
b1000 *
b1 ,
b10100000000 +
0)
#146000
b11111010000 "
b11111010000 -
b1001 *
b0 ,
b101000000000 +
1)
#148000
b1010 *
b1010000000000 +
0)
#150000
b1011 *
b10100000000000 +
1)
#152000
b1100 *
b101000000000000 +
0)
#154000
b1101 *
b1010000000000000 +
1)
#156000
b1110 *
b10100000000000000 +
0)
#158000
b1111 *
b101000000000000000 +
1)
#160000
b10000 *
b1010000000000000000 +
0)
#162000
b10001 *
b10100000000000000000 +
1)
#164000
b10010 *
b101000000000000000000 +
0)
#166000
b10011 *
b1010000000000000000000 +
1)
#168000
b10100 *
b10100000000000000000000 +
0)
#170000
b10101 *
b101000000000000000000000 +
1)
#172000
b10110 *
b1010000000000000000000000 +
0)
#174000
b10111 *
b10100000000000000000000000 +
1)
#176000
b11000 *
b101000000000000000000000000 +
0)
#178000
b11001 *
b1010000000000000000000000000 +
1)
#180000
b11010 *
b10100000000000000000000000000 +
0)
#182000
b11011 *
b101000000000000000000000000000 +
1)
#184000
b11100 *
b1010000000000000000000000000000 +
0)
#186000
b11101 *
b10100000000000000000000000000000 +
1)
#188000
b11110 *
b101000000000000000000000000000000 +
0)
#190000
b11111 *
b1010000000000000000000000000000000 +
1)
#192000
b100000 *
b10100000000000000000000000000000000 +
0)
#194000
b100001 *
b101000000000000000000000000000000000 +
1)
#196000
b100010 *
b1010000000000000000000000000000000000 +
0)
#198000
b100011 *
b10100000000000000000000000000000000000 +
1)
#200000
b100100 *
b101000000000000000000000000000000000000 +
0)
#202000
b100101 *
b1010000000000000000000000000000000000000 +
1)
#204000
b100110 *
b10100000000000000000000000000000000000000 +
0)
#206000
b100111 *
b101000000000000000000000000000000000000000 +
1)
#208000
b101000 *
b1010000000000000000000000000000000000000000 +
0)
#210000
b101001 *
b10100000000000000000000000000000000000000000 +
1)
#212000
b101010 *
b101000000000000000000000000000000000000000000 +
0)
#214000
b101011 *
b1010000000000000000000000000000000000000000000 +
1)
#216000
b101100 *
b10100000000000000000000000000000000000000000000 +
0)
#218000
b101101 *
b101000000000000000000000000000000000000000000000 +
1)
#220000
b101110 *
b1010000000000000000000000000000000000000000000000 +
0)
#222000
b101111 *
b10100000000000000000000000000000000000000000000000 +
1)
#224000
b110000 *
b101000000000000000000000000000000000000000000000000 +
0)
#226000
b110001 *
b1010000000000000000000000000000000000000000000000000 +
1)
#228000
b110010 *
b10100000000000000000000000000000000000000000000000000 +
0)
#230000
b110011 *
b101000000000000000000000000000000000000000000000000000 +
1)
#232000
b110100 *
b1010000000000000000000000000000000000000000000000000000 +
0)
#234000
b110101 *
b10100000000000000000000000000000000000000000000000000000 +
1)
#236000
b110110 *
b101000000000000000000000000000000000000000000000000000000 +
0)
#238000
b110111 *
b1010000000000000000000000000000000000000000000000000000000 +
1)
#240000
b111000 *
b10100000000000000000000000000000000000000000000000000000000 +
0)
#242000
b111001 *
b101000000000000000000000000000000000000000000000000000000000 +
1)
#244000
b111010 *
b1010000000000000000000000000000000000000000000000000000000000 +
0)
#246000
b111011 *
b10100000000000000000000000000000000000000000000000000000000000 +
1)
#248000
b111100 *
b101000000000000000000000000000000000000000000000000000000000000 +
0)
#250000
b111101 *
b1010000000000000000000000000000000000000000000000000000000000000 +
1)
#252000
b111110 *
b10100000000000000000000000000000000000000000000000000000000000000 +
0)
#254000
b10000000000000000000000000000000000000000000000000000000000000000000000000000000000000000000000000000000000000000000011111010000 "
b10000000000000000000000000000000000000000000000000000000000000000000000000000000000000000000000000000000000000000000011111010000 -
1!
b111111 *
b101000000000000000000000000000000000000000000000000000000000000000 +
1)
